PyCanOpenDevice/CanOpen_Arbitrier.py
PyCanOpenDevice/CanOpen_BusActions.py
PyCanOpenDevice/CanOpen_Callbacks.py
PyCanOpenDevice/CanOpen_Codes.py
PyCanOpenDevice/CanOpen_Device.py
PyCanOpenDevice/CanOpen_Messages.py
PyCanOpenDevice/CanOpen_Receiver.py
PyCanOpenDevice/CanOpen_Runtime.py
PyCanOpenDevice/__init__.py
PyCanOpenDevice-1.3.dist-info/METADATA
PyCanOpenDevice-1.3.dist-info/WHEEL
PyCanOpenDevice-1.3.dist-info/top_level.txt
PyCanOpenDevice-1.3.dist-info/RECORD
