Metadata-Version: 2.1
Name: PyCanOpenDevice
Version: 1.3
Summary: A Python Client to build Can Open Devices
Home-page: https://gitlab.bcmsolutions.de/bcm/pycanopendevice
Author: Jan Rosum
Author-email: jrosum1996@gmail.com
Classifier: Programming Language :: Python :: 3
Classifier: License :: OSI Approved :: MIT License
Classifier: Operating System :: OS Independent
Requires-Dist: python-can
